ercaspay/__init__.py
ercaspay/admin.py
ercaspay/apps.py
ercaspay/django.py
ercaspay/flask.py
ercaspay/main.py
ercaspay/models.py
ercaspay/urls.py
ercaspay/utility.py
ercaspay/static/style.css
ercaspay/templates/payment.html
ercaspay-1.0.0.3.dist-info/METADATA
ercaspay-1.0.0.3.dist-info/WHEEL
ercaspay-1.0.0.3.dist-info/entry_points.txt
ercaspay-1.0.0.3.dist-info/top_level.txt
ercaspay-1.0.0.3.dist-info/RECORD
