Metadata-Version: 2.2
Name: ercaspay
Version: 1.0.0.3
Summary: ercaspay plugin
Home-page: https://github.com/devfemibadmus/ercaspay
Author: Dev Femi Badmus
Author-email: devfemibadmus@gmail.com
Project-URL: Slack, https://app.slack.com/client/T083P8D99EY/C083LL3NMDZ
Project-URL: Documentation, https://ercaspay.com
Project-URL: Source Code, https://github.com/devfemibadmus/ercaspay
Keywords: ercaspay,ercas payment plugin
Classifier: Intended Audience :: Developers
Classifier: Programming Language :: Python :: 3
Classifier: Operating System :: Unix
Classifier: Operating System :: MacOS :: MacOS X
Classifier: Operating System :: Microsoft :: Windows
Requires-Dist: requests
Requires-Dist: pycryptodome
Dynamic: author
Dynamic: author-email
Dynamic: classifier
Dynamic: description
Dynamic: description-content-type
Dynamic: home-page
Dynamic: keywords
Dynamic: project-url
Dynamic: requires-dist
Dynamic: summary
